[{"draft":false,"iscjklanguage":false,"logicalName":"_index.md","relUrl":"articles/","title":"+Articles"},{"draft":false,"iscjklanguage":false,"logicalName":"_index.md","relUrl":"padya/DVG/","title":"+DVG","unicode_script":"kannada"},{"draft":false,"iscjklanguage":false,"logicalName":"_index.md","relUrl":"gadya/KS_nArAyaNAchArya/","title":"+KS ನಾರಾಯಣಾಚಾರ್ಯ"},{"draft":false,"iscjklanguage":false,"logicalName":"_index.md","relUrl":"gadya/vishvAsa/","title":"+V"},{"draft":false,"iscjklanguage":false,"logicalName":"prArthanA-phalam.md","relUrl":"gadya/prArthanA-phalam/","title":"+प्रार्थना-फलम्"},{"draft":false,"iscjklanguage":false,"logicalName":"_index.md","relUrl":"gadya/ra_gaNesha/adhi-gaNesham/","title":"+ಅಧಿ-ಗಣೇಶಮ್"},{"draft":false,"iscjklanguage":false,"logicalName":"_index.md","relUrl":"gadya/AmantraNa/","title":"+ಆಮನ್ತ್ರಣ"},{"draft":false,"iscjklanguage":false,"logicalName":"_index.md","relUrl":"","title":"+ಕನ್ನಡ"},{"draft":false,"iscjklanguage":false,"logicalName":"_index.md","relUrl":"padya/koppala-tOTa-gaNesha/kumbhasambhavIyam/","title":"+ಕುಮ್ಭ-ಸಮ್ಭವೀಯಮ್"},{"draft":false,"iscjklanguage":false,"logicalName":"_index.md","relUrl":"gIte/kuvempu/","title":"+ಕುವೆಂಪು","unicode_script":"devanagari"},{"draft":false,"iscjklanguage":false,"logicalName":"_index.md","relUrl":"padya/kuvempu/","title":"+ಕುವೆಂಪು"},{"draft":false,"iscjklanguage":false,"logicalName":"_index.md","relUrl":"padya/koppala-tOTa-gaNesha/","title":"+ಕೊಪ್ಪಲತೋಟ ಗಣೇಶ"},{"draft":false,"iscjklanguage":false,"logicalName":"_index.md","relUrl":"gadya/","title":"+ಗದ್ಯ"},{"draft":false,"iscjklanguage":false,"logicalName":"_index.md","relUrl":"gIte/","title":"+ಗೀತೆ"},{"draft":false,"iscjklanguage":false,"logicalName":"_index.md","relUrl":"gIte/gOvina_hADu/","title":"+ಗೋವಿನ ಹಾಡು","unicode_script":"kannada"},{"draft":false,"iscjklanguage":false,"logicalName":"_index.md","relUrl":"gIte/chitra-gItegaLu/","title":"+ಚಿತ್ರ-ಗೀತೆಗಳು"},{"draft":false,"iscjklanguage":false,"logicalName":"_index.md","relUrl":"gadya/tuShAra-mIrA/","title":"+ತುಷಾರ-ಮೀರಾ"},{"draft":false,"iscjklanguage":false,"logicalName":"_index.md","relUrl":"gadya/nAgamangala-shAntA/","title":"+ನಾಗಮಂಗಲ-ಶಾಂತಾ"},{"draft":false,"iscjklanguage":false,"logicalName":"nAmapada.md","relUrl":"vyAkaraNa/nAmapada/","title":"+ನಾಮಪದ"},{"draft":false,"iscjklanguage":false,"logicalName":"_index.md","relUrl":"padya/paNDitanAthAchArya/","title":"+ಪಣ್ಡಿತನಾಥಾಚಾರ್ಯ"},{"draft":false,"iscjklanguage":false,"logicalName":"_index.md","relUrl":"padya/","title":"+ಪದ್ಯ"},{"draft":false,"iscjklanguage":false,"logicalName":"_index.md","relUrl":"gadya/prakIrNa/","title":"+ಪ್ರಕೀರ್ಣ","unicode_script":"devanagari"},{"draft":false,"iscjklanguage":false,"logicalName":"_index.md","relUrl":"padya/prakIrNa/","title":"+ಪ್ರಕೀರ್ಣ"},{"draft":false,"iscjklanguage":false,"logicalName":"_index.md","relUrl":"gIte/rAjaratnam/ratnan_padagaLu/","title":"+ರತ್ನನ್ ಪದಗೊಳು"},{"draft":false,"iscjklanguage":false,"logicalName":"_index.md","relUrl":"gIte/vishvAsaH/","title":"+ವಿಶ್ಚಾಸ"},{"draft":false,"iscjklanguage":false,"logicalName":"_index.md","relUrl":"articles/saMskRta-vivAdaH/vishvavANI/","title":"+ವಿಶ್ವವಾಣೀ"},{"draft":false,"iscjklanguage":false,"logicalName":"_index.md","relUrl":"vyAkaraNa/","title":"+ವ್ಯಾಕರಣ"},{"draft":false,"iscjklanguage":false,"logicalName":"_index.md","relUrl":"padya/shatakagaLu/","title":"+ಶತಕಗಳು","unicode_script":"devanagari"},{"draft":false,"iscjklanguage":false,"logicalName":"_index.md","relUrl":"padya/shAnti-grAma-narasiMha-mUrti/","title":"+ಶಾನ್ತಿಗ್ರಾಮ-ನರಸಿಂಹ-ಮೂರ್ತಿ"},{"draft":false,"iscjklanguage":false,"logicalName":"_index.md","relUrl":"gIte/havyaka-hADugaLu/","title":"+ಹವ್ಯಕ-ಹಾಡು"},{"draft":false,"iscjklanguage":false,"logicalName":"_index.md","relUrl":"vyAkaraNa/Halagannada-Vyakarana-Praveshike_Venkatachala-Shastry/","title":"+ಹಳಗನ್ನಡ ವ್ಯಾಕರಣ ಪ್ರವೇಶಿಕೆ","unicode_script":"kannada"},{"draft":false,"iscjklanguage":false,"logicalName":"_index.md","relUrl":"articles/saMskRta-vivAdaH/hegDe-janArdana/","title":"+ಹೆಗಡೆ-ಜನಾರ್ದನ"},{"draft":false,"iscjklanguage":false,"logicalName":"_index.md","relUrl":"gadya/hebbaLalu-rAghavendra/","title":"+ಹೆಬ್ಬಳಲು-ರಾಘವೇನ್ದ್ರ"},{"draft":false,"iscjklanguage":false,"logicalName":"0.md","relUrl":"padya/DVG/kagga/0/","title":"೦","unicode_script":"kannada"},{"draft":false,"iscjklanguage":false,"logicalName":"00.md","relUrl":"vyAkaraNa/Halagannada-Vyakarana-Praveshike_Venkatachala-Shastry/00/","title":"೦೦"},{"draft":false,"iscjklanguage":false,"logicalName":"01.md","relUrl":"padya/koppala-tOTa-gaNesha/kumbhasambhavIyam/01/","title":"೦೧"},{"draft":false,"iscjklanguage":false,"logicalName":"01_pravEsha.md","relUrl":"vyAkaraNa/Halagannada-Vyakarana-Praveshike_Venkatachala-Shastry/01_pravEsha/","title":"೦೧ ಪ್ರವೇಶ"},{"draft":false,"iscjklanguage":false,"logicalName":"02_haLagannaDa_varNamAle.md","relUrl":"vyAkaraNa/Halagannada-Vyakarana-Praveshike_Venkatachala-Shastry/02_haLagannaDa_varNamAle/","title":"೦೨ ಹಳಗನ್ನಡ ವರ್ಣಮಾಲೆ"},{"draft":false,"iscjklanguage":false,"logicalName":"03_haLagannaDa_shabdarachane.md","relUrl":"vyAkaraNa/Halagannada-Vyakarana-Praveshike_Venkatachala-Shastry/03_haLagannaDa_shabdarachane/","title":"೦೩ ಹಳಗನ್ನಡ ಶಬ್ದರಚನೆ"},{"draft":false,"iscjklanguage":false,"logicalName":"04_saMdhi_-_saMdhikArya.md","relUrl":"vyAkaraNa/Halagannada-Vyakarana-Praveshike_Venkatachala-Shastry/04_saMdhi_-_saMdhikArya/","title":"೦೪ ಸಂಧಿ - ಸಂಧಿಕಾರ್ಯ"},{"draft":false,"iscjklanguage":false,"logicalName":"05_nAmapada_prakaraNa.md","relUrl":"vyAkaraNa/Halagannada-Vyakarana-Praveshike_Venkatachala-Shastry/05_nAmapada_prakaraNa/","title":"೦೫ ನಾಮಪದ ಪ್ರಕರಣ"},{"draft":false,"iscjklanguage":false,"logicalName":"06_samAsa_prakaraNa.md","relUrl":"vyAkaraNa/Halagannada-Vyakarana-Praveshike_Venkatachala-Shastry/06_samAsa_prakaraNa/","title":"೦೬ ಸಮಾಸ ಪ್ರಕರಣ"},{"draft":false,"iscjklanguage":false,"logicalName":"07_taddhitAMta_nAmapadagaLu.md","relUrl":"vyAkaraNa/Halagannada-Vyakarana-Praveshike_Venkatachala-Shastry/07_taddhitAMta_nAmapadagaLu/","title":"೦೭ ತದ್ಧಿತಾಂತ ನಾಮಪದಗಳು"},{"draft":false,"iscjklanguage":false,"logicalName":"08_AkhyAta_prakaraNa.md","relUrl":"vyAkaraNa/Halagannada-Vyakarana-Praveshike_Venkatachala-Shastry/08_AkhyAta_prakaraNa/","title":"೦೮ ಆಖ್ಯಾತ ಪ್ರಕರಣ"},{"draft":false,"iscjklanguage":false,"logicalName":"09_avyayagaLa_vichAra.md","relUrl":"vyAkaraNa/Halagannada-Vyakarana-Praveshike_Venkatachala-Shastry/09_avyayagaLa_vichAra/","title":"೦೯ ಅವ್ಯಯಗಳ ವಿಚಾರ"},{"draft":false,"iscjklanguage":false,"logicalName":"10_oMdu_prayOgapATha.md","relUrl":"vyAkaraNa/Halagannada-Vyakarana-Praveshike_Venkatachala-Shastry/10_oMdu_prayOgapATha/","title":"೧೦ ಒಂದು ಪ್ರಯೋಗಪಾಠ"},{"draft":false,"iscjklanguage":false,"logicalName":"2016-05-12__82_-_Special_PuNyakoTi.md","relUrl":"gIte/gOvina_hADu/2016-05-12__82_-_Special_PuNyakoTi/","title":"2016-05-12__82 - Special: Puṇyakōṭi"},{"draft":false,"iscjklanguage":false,"logicalName":"","relUrl":"categories/","title":"Categories"},{"draft":false,"iscjklanguage":false,"logicalName":"Ganapaty.md","relUrl":"padya/shAnti-grAma-narasiMha-mUrti/Ganapaty/","title":"Ganapaty"},{"draft":false,"iscjklanguage":false,"logicalName":"protect_sanskrit_protect_vernacular.md","relUrl":"articles/saMskRta-vivAdaH/protect_sanskrit_protect_vernacular/","title":"Protect sanskrit - protect vernacular"},{"draft":false,"iscjklanguage":false,"logicalName":"sanskrit-word-replacement-2017.md","relUrl":"articles/saMskRta-vivAdaH/sanskrit-word-replacement-2017/","title":"Sanskrit-word-replacement-2017"},{"draft":false,"iscjklanguage":false,"logicalName":"","relUrl":"tags/","title":"Tags"},{"draft":false,"iscjklanguage":false,"logicalName":"aksharamAlA.md","relUrl":"aksharamAlA/","title":"अक्षरमाला","unicode_script":"kannada"},{"draft":false,"iscjklanguage":false,"logicalName":"sandhi.md","relUrl":"vyAkaraNa/sandhi/","title":"सन्धि"},{"draft":false,"iscjklanguage":false,"logicalName":"sUrya-prakAsha_bali-pADyamI.md","relUrl":"gadya/prakIrNa/sUrya-prakAsha_bali-pADyamI/","title":"सूर्य-प्रकाश ಬಲಿಪಾಡ್ಯಮಿ"},{"draft":false,"iscjklanguage":false,"logicalName":"amma.md","relUrl":"gadya/nAgamangala-shAntA/amma/","title":"ಅಮ್ಮ"},{"draft":false,"iscjklanguage":false,"logicalName":"inti_rAdhe.md","relUrl":"gadya/ra_gaNesha/inti_rAdhe/","title":"ಇಂತಿ ರಾಧೆ"},{"draft":false,"iscjklanguage":false,"logicalName":"uddhArakana_eraDu.md","relUrl":"gadya/tuShAra-mIrA/uddhArakana_eraDu/","title":"ಉದ್ಧಾರಕನ ಎರಡು ಮುಖಗಳು"},{"draft":false,"iscjklanguage":false,"logicalName":"_index.md","relUrl":"padya/DVG/kagga/","title":"ಕಗ್ಗ","unicode_script":"devanagari"},{"draft":false,"iscjklanguage":false,"logicalName":"kaggada_kathe.md","relUrl":"padya/DVG/kagga/kaggada_kathe/","title":"ಕಗ್ಗದ ಕಥೆ","unicode_script":"kannada"},{"draft":false,"iscjklanguage":false,"logicalName":"bhaashaa-kannada.md","relUrl":"gadya/vishvAsa/bhaashaa-kannada/","title":"ಕನ್ನಡದಲ್ಲಿ ಭಾಷಾನುರಾಗದ ಪರಿಚಯ"},{"draft":false,"iscjklanguage":false,"logicalName":"kAyau_shrI-gauri.md","relUrl":"gIte/kAyau_shrI-gauri/","title":"ಕಾಯೌ ಶ್ರೀ ಗೌರಿ"},{"draft":false,"iscjklanguage":false,"logicalName":"kAvyadalli_ramaNa.md","relUrl":"gadya/prakIrNa/kAvyadalli_ramaNa/","title":"ಕಾವ್ಯದಲ್ಲಿ ರಮಣ"},{"draft":false,"iscjklanguage":false,"logicalName":"_index.md","relUrl":"gadya/kulakaraNi-nIlakaNThaH/","title":"ಕುಲಕರಣಿ-ನೀಲಕಣ್ಠಃ"},{"draft":false,"iscjklanguage":false,"logicalName":"_index.md","relUrl":"gadya/ku-ve-puTTappa/","title":"ಕುವೆಂಪು"},{"draft":false,"iscjklanguage":false,"logicalName":"_index.md","relUrl":"padya/narasiMha-svAmI/","title":"ಕೆ. ಎಸ್. ನರಸಿಂಹ ಸ್ವಾಮಿ"},{"draft":false,"iscjklanguage":false,"logicalName":"kere_Eri.md","relUrl":"padya/shAnti-grAma-narasiMha-mUrti/kere_Eri/","title":"ಕೆರೆ ಏರಿ"},{"draft":false,"iscjklanguage":false,"logicalName":"kosha-sukha.md","relUrl":"gadya/nAgamangala-shAntA/kosha-sukha/","title":"ಕೋಶ ಓದುವ ಸುಖ"},{"draft":false,"iscjklanguage":false,"logicalName":"kriyApada.md","relUrl":"vyAkaraNa/kriyApada/","title":"ಕ್ರಿಯಾಪದ","unicode_script":"devanagari"},{"draft":false,"iscjklanguage":false,"logicalName":"gaNesha-parivAra.md","relUrl":"gadya/maNTapa-prabhAkaropAdhyAyaH/gaNesha-parivAra/","title":"ಗಣೇಶಪರಿವಾರ"},{"draft":false,"iscjklanguage":false,"logicalName":"gAndhi.md","relUrl":"padya/shAnti-grAma-narasiMha-mUrti/gAndhi/","title":"ಗಾಂಧಿ"},{"draft":false,"iscjklanguage":false,"logicalName":"gOrlana_gOLu.md","relUrl":"padya/shAnti-grAma-narasiMha-mUrti/gOrlana_gOLu/","title":"ಗೋರ್ಲನ ಗೋಳು"},{"draft":false,"iscjklanguage":false,"logicalName":"shashi_dvg-bhAShA-shilpa.md","relUrl":"articles/shashi_dvg-bhAShA-shilpa/","title":"ಡಿ.ವಿ.ಜಿ. ಅವರ ಭಾಷಾಶಿಲ್ಪ"},{"draft":false,"iscjklanguage":false,"logicalName":"tabbaliyu_nInAde_magane.md","relUrl":"gIte/gOvina_hADu/tabbaliyu_nInAde_magane/","title":"ತಬ್ಬಲಿಯು ನೀನಾದೆ ಮಗನೆ ಚಿತ್ರದಲ್ಲಿ"},{"draft":false,"iscjklanguage":false,"logicalName":"tUgirO_svAmiyA.md","relUrl":"padya/shAnti-grAma-narasiMha-mUrti/tUgirO_svAmiyA/","title":"ತೂಗಿರೋ ಸ್ವಾಮಿಯಾ"},{"draft":false,"iscjklanguage":false,"logicalName":"tejasvi-anantamUrti.md","relUrl":"gadya/vyAmishra/tejasvi-anantamUrti/","title":"ತೇಜಸ್ವಿ-ಅನನ್ತಮೂರ್ತಿ"},{"draft":false,"iscjklanguage":false,"logicalName":"tejasvi-patram.md","relUrl":"gadya/ku-ve-puTTappa/tejasvi-patram/","title":"ತೇಜಸ್ವಿ-ಪತ್ರಮ್"},{"draft":false,"iscjklanguage":false,"logicalName":"toTTalu-hADu.md","relUrl":"gIte/havyaka-hADugaLu/toTTalu-hADu/","title":"ತೊಟ್ಟಲು-ಪೂಜೆ","unicode_script":"kannada"},{"draft":false,"iscjklanguage":false,"logicalName":"dUrake_dUrake.md","relUrl":"gIte/kuvempu/dUrake_dUrake/","title":"ದೂರಕೆ ದೂರಕೆ","unicode_script":"kannada"},{"draft":false,"iscjklanguage":false,"logicalName":"dRShTi-dAna.md","relUrl":"padya/paNDitanAthAchArya/dRShTi-dAna/","title":"ದೃಷ್ಟಿ-ದಾನ"},{"draft":false,"iscjklanguage":false,"logicalName":"naDu-gannaDa-pATha.md","relUrl":"gIte/gOvina_hADu/naDu-gannaDa-pATha/","title":"ನಡುಗನ್ನಡಪಾಠ"},{"draft":false,"iscjklanguage":false,"logicalName":"namma_Ura_rasikaru.md","relUrl":"gadya/hebbaLalu-rAghavendra/namma_Ura_rasikaru/","title":"ನಮ್ಮ ಊರ ರಸಿಕರು"},{"draft":false,"iscjklanguage":false,"logicalName":"nijalinga-shataka.md","relUrl":"padya/shatakagaLu/nijalinga-shataka/","title":"ನಿಜಲಿಂಗಶತಕ","unicode_script":"devanagari"},{"draft":false,"iscjklanguage":false,"logicalName":"nInalladE.md","relUrl":"padya/shAnti-grAma-narasiMha-mUrti/nInalladE/","title":"ನೀನಲ್ಲದೇ"},{"draft":false,"iscjklanguage":false,"logicalName":"nIvallave.md","relUrl":"padya/narasiMha-svAmI/nIvallave/","title":"ನೀವ್ ಅಲ್ಲವೇ"},{"draft":false,"iscjklanguage":false,"logicalName":"paNDita.md","relUrl":"padya/shAnti-grAma-narasiMha-mUrti/paNDita/","title":"ಪಂಡಿತ"},{"draft":false,"iscjklanguage":false,"logicalName":"pannIru-dAni.md","relUrl":"gadya/nAgamangala-shAntA/pannIru-dAni/","title":"ಪನ್ನೀರುದಾನಿ"},{"draft":false,"iscjklanguage":false,"logicalName":"pampA-shataka.md","relUrl":"padya/shatakagaLu/pampA-shataka/","title":"ಪಂಪಾಶತಕ","unicode_script":"devanagari"},{"draft":false,"iscjklanguage":false,"logicalName":"_index.md","relUrl":"padya/narasiMhAchAr/","title":"ಪು ತಿ ನರಸಿಂಹಾಚಾರ್","unicode_script":"kannada"},{"draft":false,"iscjklanguage":false,"logicalName":"puNgnUra_maduve.md","relUrl":"padya/shAnti-grAma-narasiMha-mUrti/puNgnUra_maduve/","title":"ಪುಂಗ್ನೂರ ಮದುವೆ"},{"draft":false,"iscjklanguage":false,"logicalName":"prabhUji.md","relUrl":"padya/shAnti-grAma-narasiMha-mUrti/prabhUji/","title":"ಪ್ರಭೂಜಿ"},{"draft":false,"iscjklanguage":false,"logicalName":"prAtipadika.md","relUrl":"vyAkaraNa/prAtipadika/","title":"ಪ್ರಾತಿಪದಿಕ"},{"draft":false,"iscjklanguage":false,"logicalName":"bali-pADyamI.md","relUrl":"gadya/kulakaraNi-nIlakaNThaH/bali-pADyamI/","title":"ಬಲಿಪಾಡ್ಯಮಿ"},{"draft":false,"iscjklanguage":false,"logicalName":"bhAnigondu_elle.md","relUrl":"gIte/chitra-gItegaLu/bhAnigondu_elle/","title":"ಭಾನಿಗೊಂದು ಎಲ್ಲೆ "},{"draft":false,"iscjklanguage":false,"logicalName":"bhAnumati.md","relUrl":"gadya/KS_nArAyaNAchArya/bhAnumati/","title":"ಭಾನುಮತಿ"},{"draft":false,"iscjklanguage":false,"logicalName":"bhAShA-rAjakIya-niShedha.md","relUrl":"articles/saMskRta-vivAdaH/vishvavANI/bhAShA-rAjakIya-niShedha/","title":"ಭಾಷಾರಾಜಕೀಯ-ನಿಷೇಧ"},{"draft":false,"iscjklanguage":false,"logicalName":"_index.md","relUrl":"gadya/maNTapa-prabhAkaropAdhyAyaH/","title":"ಮಂಡಪ-ಪ್ರಭಾಕರೋಪಾಧ್ಯಾಯ"},{"draft":false,"iscjklanguage":false,"logicalName":"mAtR-devo_bhava.md","relUrl":"gadya/prakIrNa/mAtR-devo_bhava/","title":"ಮಾತೃದೇವೋ ಭವ","unicode_script":"devanagari"},{"draft":false,"iscjklanguage":false,"logicalName":"yathoktakArI_tirumAL-isai.md","relUrl":"gadya/nAgamangala-shAntA/yathoktakArI_tirumAL-isai/","title":"ಯಥೋಕ್ತಕಾರಿ - ತಿರುಮಳಿಶೈ"},{"draft":false,"iscjklanguage":false,"logicalName":"yArigU_hELONu_byADa.md","relUrl":"padya/shAnti-grAma-narasiMha-mUrti/yArigU_hELONu_byADa/","title":"ಯಾರಿಗೂ ಹೇಳೋಣು ಬ್ಯಾಡ"},{"draft":false,"iscjklanguage":false,"logicalName":"yAru_tiLiyaru.md","relUrl":"gIte/chitra-gItegaLu/yAru_tiLiyaru/","title":"ಯಾರು ತಿಳಿಯರು"},{"draft":false,"iscjklanguage":false,"logicalName":"raxA-shataka.md","relUrl":"padya/shatakagaLu/raxA-shataka/","title":"ರಕ್ಷಾ ಶತಕ"},{"draft":false,"iscjklanguage":false,"logicalName":"rangavallI.md","relUrl":"padya/narasiMhAchAr/rangavallI/","title":"ರಂಗವಲ್ಲೀ","unicode_script":"kannada"},{"draft":false,"iscjklanguage":false,"logicalName":"ratnan_prapancha.md","relUrl":"gIte/rAjaratnam/ratnan_padagaLu/ratnan_prapancha/","title":"ರತ್ನನ್ ಪ್ರಪಂಚ"},{"draft":false,"iscjklanguage":false,"logicalName":"_index.md","relUrl":"gadya/ra_gaNesha/","title":"ರಾ ಗಣೇಶ"},{"draft":false,"iscjklanguage":false,"logicalName":"_index.md","relUrl":"gIte/rAjaratnam/","title":"ರಾಜರತ್ನಂ ಜಿ ಪಿ"},{"draft":false,"iscjklanguage":false,"logicalName":"rAjA-rAmanu-rAjanu-alla.md","relUrl":"gIte/vishvAsaH/rAjA-rAmanu-rAjanu-alla/","title":"ರಾಜಾರಾಮನು","unicode_script":"kannada"},{"draft":false,"iscjklanguage":false,"logicalName":"rAvi-pAra.md","relUrl":"gadya/nAgamangala-shAntA/rAvi-pAra/","title":"ರಾವೀ ಪಾರ್‌"},{"draft":false,"iscjklanguage":false,"logicalName":"langoTi-meravaNige.md","relUrl":"gadya/nAgamangala-shAntA/langoTi-meravaNige/","title":"ಲಂಗೋಟಿ ಮೆರವಣಿಗೆ"},{"draft":false,"iscjklanguage":false,"logicalName":"_index.md","relUrl":"gadya/vyAmishra/","title":"ವ್ಯಾಮಿಶ್ರ"},{"draft":false,"iscjklanguage":false,"logicalName":"shiva-pratiShThA_1909.md","relUrl":"gadya/AmantraNa/shiva-pratiShThA_1909/","title":"ಶಿವ-ಪ್ರತಿಷ್ಠಾ ೧೯೦೯"},{"draft":false,"iscjklanguage":false,"logicalName":"shrInivAsa-rAju-sAra.md","relUrl":"gadya/ra_gaNesha/adhi-gaNesham/shrInivAsa-rAju-sAra/","title":"ಶ್ರೀನಿವಾಸ-ರಾಜು-ಸಾರ"},{"draft":false,"iscjklanguage":false,"logicalName":"shrIshaila-pravAsa.md","relUrl":"gadya/kulakaraNi-nIlakaNThaH/shrIshaila-pravAsa/","title":"ಶ್ರೀಶೈಲ-ಪ್ರವಾಸ"},{"draft":false,"iscjklanguage":false,"logicalName":"satyanArAyaNa-kathA.md","relUrl":"padya/prakIrNa/satyanArAyaNa-kathA/","title":"ಸತ್ಯನಾರಾಯಣಕಥಾ","unicode_script":"kannada"},{"draft":false,"iscjklanguage":false,"logicalName":"samAsa.md","relUrl":"vyAkaraNa/samAsa/","title":"ಸಮಾಸ","unicode_script":"devanagari"},{"draft":false,"iscjklanguage":false,"logicalName":"_index.md","relUrl":"articles/saMskRta-vivAdaH/","title":"ಸಂಸ್ಕೃತ-ವಿವಾದಃ"},{"draft":false,"iscjklanguage":false,"logicalName":"saMskRta-shabda-tiraskAra.md","relUrl":"articles/saMskRta-vivAdaH/hegDe-janArdana/saMskRta-shabda-tiraskAra/","title":"ಸಂಸ್ಕೃತ-ಶಬ್ದ-ತಿರಸ್ಕಾರ"},{"draft":false,"iscjklanguage":false,"logicalName":"saMskRtada_anna.md","relUrl":"articles/saMskRta-vivAdaH/hegDe-janArdana/saMskRtada_anna/","title":"ಸಂಸ್ಕೃತದ ಅನ್ನ"},{"draft":false,"iscjklanguage":false,"logicalName":"siridhavA_mAdhavA.md","relUrl":"padya/shAnti-grAma-narasiMha-mUrti/siridhavA_mAdhavA/","title":"ಸಿರಿಧವಾ ಮಾಧವಾ"},{"draft":false,"iscjklanguage":false,"logicalName":"sUlibele-chakravarti-2023.md","relUrl":"gadya/ra_gaNesha/adhi-gaNesham/sUlibele-chakravarti-2023/","title":"ಸೂಲಿಬೆಲೆ-ಚಕ್ರವರ್ತಿ-2023"},{"draft":false,"iscjklanguage":false,"logicalName":"somashekharaninda-shashi-stuti.md","relUrl":"gadya/ra_gaNesha/adhi-gaNesham/somashekharaninda-shashi-stuti/","title":"ಸೋಮಶೆಖರನಿನ್ದ ಶಶಿ-ಸ್ತುತಿ"},{"draft":false,"iscjklanguage":false,"logicalName":"someshvara-shataka.md","relUrl":"padya/shatakagaLu/someshvara-shataka/","title":"ಸೋಮೇಶ್ವರಶತಕ","unicode_script":"devanagari"},{"draft":false,"iscjklanguage":false,"logicalName":"hindustAnavu_endU_mareyada.md","relUrl":"gIte/chitra-gItegaLu/hindustAnavu_endU_mareyada/","title":"ಹಿನ್ದುಸ್ಥಾನವು ಎನ್ದೂ ಮರೆಯದ"},{"draft":false,"iscjklanguage":false,"logicalName":"hOdre_hOgli_innondu_madve.md","relUrl":"padya/shAnti-grAma-narasiMha-mUrti/hOdre_hOgli_innondu_madve/","title":"ಹೋದ್ರೆ ಹೋಗ್ಲಿ ಇನ್ನೊಂದು ಮದ್ವೆ"},{"draft":false,"iscjklanguage":false,"logicalName":"search.md","relUrl":"search/","title":"🥽🔦"}]